polka/__init__.py
polka/core.py
polka/miriade.py
polka/models.py
polka/plotting.py
space_polka-0.1.3.dist-info/LICENSE
space_polka-0.1.3.dist-info/METADATA
space_polka-0.1.3.dist-info/WHEEL
space_polka-0.1.3.dist-info/RECORD
